hidroconta/__init__.py
hidroconta/api.py
hidroconta/endpoints.py
hidroconta/hist.py
hidroconta/time.py
hidroconta/types.py
hidroconta-1.8.0.dist-info/METADATA
hidroconta-1.8.0.dist-info/WHEEL
hidroconta-1.8.0.dist-info/top_level.txt
hidroconta-1.8.0.dist-info/RECORD
