Metadata-Version: 2.2
Name: hidroconta
Version: 1.8.0
Summary: Facilitate access to Demeter REST interface endpoints, provided by Hidroconta S.A.U.
Author: JavierL
Author-email: javier.lopez@hidroconta.com
Classifier: Programming Language :: Python :: 3
Classifier: License :: OSI Approved :: MIT License
Classifier: Operating System :: OS Independent
Requires-Python: >=3.9
Requires-Dist: pandas>=1.3.5
Requires-Dist: requests>=2.26.0
Requires-Dist: datetime>=5.5
Dynamic: author
Dynamic: author-email
Dynamic: classifier
Dynamic: description
Dynamic: description-content-type
Dynamic: requires-dist
Dynamic: requires-python
Dynamic: summary
